missingdata/__init__.py
missingdata/missing.py
missing_py-0.0.1.dist-info/LICENSE
missing_py-0.0.1.dist-info/METADATA
missing_py-0.0.1.dist-info/WHEEL
missing_py-0.0.1.dist-info/top_level.txt
missing_py-0.0.1.dist-info/RECORD
