Metadata-Version: 2.1
Name: missing-py
Version: 0.0.1
Summary: Missing data handling package
Home-page: https://github.com/pypa/sampleproject
Author: Parth Bansal
Author-email: pbansal_be17@thapar.edu
License: UNKNOWN
Platform: UNKNOWN
Classifier: Programming Language :: Python :: 3
Classifier: License :: OSI Approved :: MIT License
Classifier: Operating System :: OS Independent
Requires-Python: >=3.6
